django_trackmate/__init__.py
django_trackmate/admin.py
django_trackmate/apps.py
django_trackmate/main.py
django_trackmate/middleware.py
django_trackmate/models.py
django_trackmate/signals.py
django_trackmate/tests.py
django_trackmate/utils.py
django_trackmate/migrations/__init__.py
django_trackmate-0.2.0.dist-info/LICENSE
django_trackmate-0.2.0.dist-info/METADATA
django_trackmate-0.2.0.dist-info/WHEEL
django_trackmate-0.2.0.dist-info/top_level.txt
django_trackmate-0.2.0.dist-info/RECORD
